Metadata-Version: 2.1
Name: textframe
Version: 0.0.22
Summary: An ASCII plain text table renderer.
Author-email: Guy de Winton <guy@codehippie.io>
Project-URL: Homepage, https://gitlab.com/guydewinton/textframe
Project-URL: Bug Tracker, https://gitlab.com/guydewinton/textframe/issues
Classifier: Programming Language :: Python :: 3
Classifier: License :: OSI Approved :: MIT License
Classifier: Operating System :: OS Independent
Requires-Python: >=3
License-File: LICENCE
